dbspace/__init__.py
dbspace/__testing__/readout/DSV.py
dbspace/control/DTI.py
dbspace/control/DTI_support.py
dbspace/control/VirtTract.py
dbspace/control/__init__.py
dbspace/control/dyn_osc.py
dbspace/control/network_action.py
dbspace/control/offline_segments.py
dbspace/control/stream_buffers.py
dbspace/readout/BR_DataFrame.py
dbspace/readout/ClinVect.py
dbspace/readout/OBands.py
dbspace/readout/__init__.py
dbspace/readout/decoder.py
dbspace/readout/phases.py
dbspace/signal/PAC/PyPAC.py
dbspace/signal/PAC/README
dbspace/signal/PAC/SyntheticSignalTesting.py
dbspace/signal/PAC/__init__.py
dbspace/signal/PRE/__init__.py
dbspace/signal/PRE/tree_view.py
dbspace/signal/__init__.py
dbspace/signal/dEEG/neigh_mont.py
dbspace/signal/dLFP/README.md
dbspace/signal/dLFP/__init__.py
dbspace/signal/dLFP/amp_tf_models.py
dbspace/signal/dLFP/brain_amp_model.py
dbspace/signal/dLFP/db_stim.py
dbspace/signal/dLFP/diff_amp_model.py
dbspace/signal/dLFP/gcr.py
dbspace/signal/dLFP/impedances.py
dbspace/signal/dLFP/ipg_stim.py
dbspace/signal/dLFP/sig_amp_model.py
dbspace/signal/hots.py
dbspace/signal/oscillations.py
dbspace/signal/spot_check.py
dbspace/utils/__init__.py
dbspace/utils/costs.py
dbspace/utils/functions.py
dbspace/utils/io/brPY/__init__.py
dbspace/utils/io/brPY/brMiscFxns.py
dbspace/utils/io/brPY/brpylib.py
dbspace/utils/io/br_io.py
dbspace/utils/io/deeg_io.py
dbspace/utils/io/pcs.py
dbspace/utils/io/xlt_io.py
dbspace/utils/r_pca/LICENSE
dbspace/utils/r_pca/__init__.py
dbspace/utils/r_pca/robust_pca.py
dbspace/utils/stats.py
dbspace/utils/structures.py
dbspace/viz/MM/EEG_Viz.py
dbspace/viz/MM/intraop.py
dbspace/viz/TF/TS_spectrogram.py
dbspace/viz/__init__.py
dbspace-0.4.0.dist-info/LICENSE
dbspace-0.4.0.dist-info/METADATA
dbspace-0.4.0.dist-info/WHEEL
dbspace-0.4.0.dist-info/RECORD
