Metadata-Version: 2.1
Name: dbspace
Version: 0.4.0
Summary: Library for data-congruent, model-centric DBS Research
License: GLPv3
Author: Vineet Tiruvadi
Author-email: vineet.tiruvadi@gmail.com
Requires-Python: ==3.8.17
Classifier: License :: Other/Proprietary License
Classifier: Programming Language :: Python :: 3
Requires-Dist: matplotlib (>=3.4.3,<4.0.0)
Requires-Dist: nibabel (>=3.2.1,<4.0.0)
Requires-Dist: nilearn (>=0.8.1,<0.9.0)
Requires-Dist: numpy (>=1.21.2,<2.0.0)
Requires-Dist: scikit-learn (>=0.24.2,<0.25.0)
Requires-Dist: scipy (>=1.7.1,<2.0.0)
Requires-Dist: seaborn (>=0.11.2,<0.12.0)
Requires-Dist: setuptools (==49.2.1)
